bw_essentials/__init__.py
bw_essentials/constants/__init__.py
bw_essentials/constants/services.py
bw_essentials/data_loch/__init__.py
bw_essentials/data_loch/data_loch.py
bw_essentials/email_client/__init__.py
bw_essentials/email_client/email_client.py
bw_essentials/notifications/__init__.py
bw_essentials/notifications/teams_notification_schemas.py
bw_essentials/notifications/teams_notifications.py
bw_essentials/s3_utils/__init__.py
bw_essentials/s3_utils/s3_utils.py
bw_essentials/services/__init__.py
bw_essentials/services/api_client.py
bw_essentials/services/broker.py
bw_essentials/services/compliance.py
bw_essentials/services/job_scheduler.py
bw_essentials/services/market_pricer.py
bw_essentials/services/master_data.py
bw_essentials/services/model_portfolio_reporting.py
bw_essentials/services/notification.py
bw_essentials/services/payment.py
bw_essentials/services/portfolio_catalogue.py
bw_essentials/services/portfolio_content.py
bw_essentials/services/trade_placement.py
bw_essentials/services/user_app.py
bw_essentials/services/user_portfolio.py
bw_essentials/services/user_portfolio_reporting.py
bw_essentials_core-0.1.34.dist-info/METADATA
bw_essentials_core-0.1.34.dist-info/WHEEL
bw_essentials_core-0.1.34.dist-info/top_level.txt
bw_essentials_core-0.1.34.dist-info/RECORD
